{
  "header": {
    "allowed": [
      "minicart",
      "login",
      "menu-link",
      "category-menu",
      "search-bar",
      "theme",
      "user-address",
      "menu",
      "telemarketing",
      "logo",
      "header-desktop",
      "header-mobile"
    ],
    "component": "index"
  },
  "header.full": {},
  "header-desktop": {
    "allowed": [
      "menu-link",
      "theme",
      "user-address",
      "menu",
      "category-menu",
      "header-row"
    ],
    "component": "Layout",
    "unstable__layoutMode": "dynamic"
  },
  "header-mobile": {
    "allowed": [
      "header-row"
    ],
    "component": "Layout",
    "unstable__layoutMode": "dynamic"
  },
  "_": {
    "component": "Spacer"
  },
  "header-row": {
    "allowed": [
      "telemarketing",
      "logo",
      "minicart",
      "login",
      "search-bar",
      "menu-link",
      "category-menu",
      "search-bar",
      "theme",
      "user-address",
      "menu",
      "_"
    ],
    "component": "Row",
    "unstable__layoutMode": "dynamic"
  },
  "unstable--header-border": {
    "component": "Border"
  },
  "theme": {}
}